vanitas/__init__.py
vanitas-1.0.dist-info/METADATA
vanitas-1.0.dist-info/WHEEL
vanitas-1.0.dist-info/top_level.txt
vanitas-1.0.dist-info/RECORD
